sysyphus/__init__.py
sysyphus/models/__init__.py
sysyphus/models/boulder.py
sysyphus/models/meteorite.py
sysyphus/scripts/__init__.py
sysyphus/scripts/preprocessing.py
sysyphus/scripts/remote_load.py
sysyphus/scripts/rendering.py
sysyphus/scripts/search.py
sysyphus/scripts/user_requests.py
sysyphus-0.1.2.dist-info/LICENSE
sysyphus-0.1.2.dist-info/METADATA
sysyphus-0.1.2.dist-info/WHEEL
sysyphus-0.1.2.dist-info/top_level.txt
sysyphus-0.1.2.dist-info/RECORD
