Metadata-Version: 2.1
Name: sysyphus
Version: 0.1.2
Summary: Structured meteorite data access using MetBull: Query, filter, and analyze with ease.
Home-page: https://github.com/Psemp/sysyphus.git
Author: Pierre Sempéré
Author-email: pierre.sempere.01@gmail.com
Classifier: Programming Language :: Python :: 3
Classifier: Programming Language :: Python :: 3.10
Classifier: License :: OSI Approved :: MIT License
Classifier: Operating System :: OS Independent
Requires-Python: >=3.10
License-File: LICENSE
Requires-Dist: pandas
Requires-Dist: numpy
Requires-Dist: beautifulsoup4
Requires-Dist: requests
Requires-Dist: tqdm
